<mxfile host="app.diagrams.net" agent="Mozilla/5.0 (Windows NT 10.0; Win64; x64) AppleWebKit/537.36 (KHTML, like Gecko) Chrome/143.0.0.0 Safari/537.36" version="29.2.10">
  <diagram id="Activity_26_Peneliti_Pemilihan" name="Activity 26: Peneliti Pemilihan (Swimlane)">
    <mxGraphModel dx="1603" dy="865" grid="1" gridSize="10" guides="1" tooltips="1" connect="1" arrows="1" fold="1" page="1" pageScale="1" pageWidth="1400" pageHeight="1800" math="0" shadow="0">
      <root>
        <mxCell id="0" />
        <mxCell id="1" parent="0" />
        <mxCell id="swimlane_peneliti" parent="1" style="swimlane;whiteSpace=wrap;html=1;fillColor=#dae8fc;strokeColor=#6c8ebf;fontStyle=1;fontSize=14;" value="Peneliti" vertex="1">
          <mxGeometry height="570" width="480" x="40" y="40" as="geometry" />
        </mxCell>
        <mxCell id="start" parent="swimlane_peneliti" style="ellipse;whiteSpace=wrap;html=1;fillColor=#000000;strokeColor=none;" value="" vertex="1">
          <mxGeometry height="30" width="30" x="80" y="60" as="geometry" />
        </mxCell>
        <mxCell id="peneliti_open_booking" parent="swimlane_peneliti" style="rounded=1;whiteSpace=wrap;html=1;fillColor=#f3e5f5;strokeColor=#7b1fa2;" value="Membuka Booking untuk Pemilihan" vertex="1">
          <mxGeometry height="50" width="260" x="170" y="50" as="geometry" />
        </mxCell>
        <mxCell id="peneliti_select_radio" parent="swimlane_peneliti" style="rhombus;whiteSpace=wrap;html=1;fillColor=#fff2cc;strokeColor=#d6b656;" value="Memilih Radio Button?" vertex="1">
          <mxGeometry height="80" width="180" x="150" y="130" as="geometry" />
        </mxCell>
        <mxCell id="peneliti_option1" parent="swimlane_peneliti" style="rounded=1;whiteSpace=wrap;html=1;fillColor=#f3e5f5;strokeColor=#7b1fa2;" value="Penghitung Wajib Pajak" vertex="1">
          <mxGeometry height="30" width="155" x="85" y="250" as="geometry" />
        </mxCell>
        <mxCell id="peneliti_option2" parent="swimlane_peneliti" style="rounded=1;whiteSpace=wrap;html=1;fillColor=#f3e5f5;strokeColor=#7b1fa2;" value="STPD Kurang Bayar" vertex="1">
          <mxGeometry height="30" width="170" x="280" y="250" as="geometry" />
        </mxCell>
        <mxCell id="peneliti_option3" parent="swimlane_peneliti" style="rounded=1;whiteSpace=wrap;html=1;fillColor=#f3e5f5;strokeColor=#7b1fa2;" value="Dihitung Sendiri" vertex="1">
          <mxGeometry height="40" width="150" x="50" y="310" as="geometry" />
        </mxCell>
        <mxCell id="peneliti_option4" parent="swimlane_peneliti" style="rounded=1;whiteSpace=wrap;html=1;fillColor=#f3e5f5;strokeColor=#7b1fa2;" value="Lainnya Penghitung WP" vertex="1">
          <mxGeometry height="50" width="200" x="260" y="410" as="geometry" />
        </mxCell>
        <mxCell id="peneliti_view_result" parent="swimlane_peneliti" style="rounded=1;whiteSpace=wrap;html=1;fillColor=#f3e5f5;strokeColor=#7b1fa2;" value="Melihat Status Pemilihan" vertex="1">
          <mxGeometry height="50" width="200" x="70" y="460" as="geometry" />
        </mxCell>
        <mxCell id="end" parent="swimlane_peneliti" style="ellipse;whiteSpace=wrap;html=1;fillColor=#000000;strokeColor=#000000;strokeWidth=2;" value="" vertex="1">
          <mxGeometry height="30" width="30" x="285" y="520" as="geometry" />
        </mxCell>
        <mxCell id="swimlane_system" parent="1" style="swimlane;whiteSpace=wrap;html=1;fillColor=#e1d5e7;strokeColor=#9673a6;fontStyle=1;fontSize=14;" value="Sistem" vertex="1">
          <mxGeometry height="570" width="360" x="520" y="40" as="geometry" />
        </mxCell>
        <mxCell id="sys_get_data" parent="swimlane_system" style="rounded=1;whiteSpace=wrap;html=1;fillColor=#f8cecc;strokeColor=#b85450;" value="Mengambil Data Booking&#xa;(p_1_verifikasi)" vertex="1">
          <mxGeometry height="60" width="200" x="20" y="45" as="geometry" />
        </mxCell>
        <mxCell id="sys_save_selection" parent="swimlane_system" style="rounded=1;whiteSpace=wrap;html=1;fillColor=#f8cecc;strokeColor=#b85450;" value="Menyimpan Pemilihan&#xa;(Update p_1_verifikasi&#xa;SET pemilihan=value)" vertex="1">
          <mxGeometry height="90" width="200" x="140" y="260" as="geometry" />
        </mxCell>
        <mxCell id="sys_show_success" parent="swimlane_system" style="rounded=1;whiteSpace=wrap;html=1;fillColor=#d5e8d4;strokeColor=#82b366;" value="Menampilkan Pesan Sukses" vertex="1">
          <mxGeometry height="50" width="200" x="60" y="410" as="geometry" />
        </mxCell>
        <mxCell id="edge1" edge="1" parent="1" source="start" style="edgeStyle=orthogonalEdgeStyle;rounded=0;orthogonalLoop=1;jettySize=auto;html=1;" target="peneliti_open_booking" value="">
          <mxGeometry relative="1" as="geometry" />
        </mxCell>
        <mxCell id="edge2" edge="1" parent="1" source="peneliti_open_booking" style="edgeStyle=orthogonalEdgeStyle;rounded=0;orthogonalLoop=1;jettySize=auto;html=1;exitX=1;exitY=0.5;entryX=0;entryY=0.5;" target="sys_get_data" value="">
          <mxGeometry relative="1" as="geometry" />
        </mxCell>
        <mxCell id="edge3" edge="1" parent="1" source="sys_get_data" style="edgeStyle=orthogonalEdgeStyle;rounded=0;orthogonalLoop=1;jettySize=auto;html=1;exitX=0.5;exitY=1;entryX=1;entryY=0.5;exitDx=0;exitDy=0;" target="peneliti_select_radio" value="">
          <mxGeometry relative="1" as="geometry">
            <Array as="points">
              <mxPoint x="640" y="200" />
              <mxPoint x="380" y="200" />
            </Array>
          </mxGeometry>
        </mxCell>
        <mxCell id="edge4" edge="1" parent="1" source="peneliti_select_radio" style="edgeStyle=orthogonalEdgeStyle;rounded=0;orthogonalLoop=1;jettySize=auto;html=1;exitX=0.5;exitY=1;entryX=0.5;entryY=0;exitDx=0;exitDy=0;" target="peneliti_option1" value="Option 1">
          <mxGeometry relative="1" as="geometry" />
        </mxCell>
        <mxCell id="edge5" edge="1" parent="1" source="peneliti_select_radio" style="edgeStyle=orthogonalEdgeStyle;rounded=0;orthogonalLoop=1;jettySize=auto;html=1;exitX=1;exitY=1;entryX=0.5;entryY=0;exitDx=0;exitDy=0;" target="peneliti_option2" value="Option 2">
          <mxGeometry relative="1" as="geometry" />
        </mxCell>
        <mxCell id="edge6" edge="1" parent="1" source="peneliti_select_radio" style="edgeStyle=orthogonalEdgeStyle;rounded=0;orthogonalLoop=1;jettySize=auto;html=1;entryX=0.5;entryY=0;" target="peneliti_option3" value="Option 3">
          <mxGeometry relative="1" as="geometry">
            <Array as="points">
              <mxPoint x="220" y="260" />
              <mxPoint x="100" y="260" />
              <mxPoint x="100" y="350" />
            </Array>
          </mxGeometry>
        </mxCell>
        <mxCell id="edge7" edge="1" parent="1" source="peneliti_select_radio" style="edgeStyle=orthogonalEdgeStyle;rounded=0;orthogonalLoop=1;jettySize=auto;html=1;exitX=0;exitY=0.5;entryX=0;entryY=0.5;exitDx=0;exitDy=0;entryDx=0;entryDy=0;" target="peneliti_option4" value="Option 4">
          <mxGeometry relative="1" as="geometry">
            <Array as="points">
              <mxPoint x="190" y="223" />
              <mxPoint x="50" y="223" />
              <mxPoint x="50" y="400" />
              <mxPoint x="230" y="400" />
              <mxPoint x="230" y="475" />
            </Array>
          </mxGeometry>
        </mxCell>
        <mxCell id="edge8" edge="1" parent="1" source="peneliti_option1" style="edgeStyle=orthogonalEdgeStyle;rounded=0;orthogonalLoop=1;jettySize=auto;html=1;exitX=1;exitY=0.5;entryX=0;entryY=0.5;" target="sys_save_selection" value="">
          <mxGeometry relative="1" as="geometry">
            <Array as="points">
              <mxPoint x="300" y="305" />
              <mxPoint x="300" y="380" />
              <mxPoint x="420" y="380" />
              <mxPoint x="420" y="345" />
            </Array>
          </mxGeometry>
        </mxCell>
        <mxCell id="edge9" edge="1" parent="1" source="peneliti_option2" style="edgeStyle=orthogonalEdgeStyle;rounded=0;orthogonalLoop=1;jettySize=auto;html=1;exitX=1;exitY=0.5;entryX=0;entryY=0.5;exitDx=0;exitDy=0;" target="sys_save_selection" value="">
          <mxGeometry relative="1" as="geometry">
            <Array as="points">
              <mxPoint x="490" y="345" />
            </Array>
          </mxGeometry>
        </mxCell>
        <mxCell id="edge10" edge="1" parent="1" source="peneliti_option3" style="edgeStyle=orthogonalEdgeStyle;rounded=0;orthogonalLoop=1;jettySize=auto;html=1;exitX=1;exitY=0.5;entryX=0;entryY=0.5;" target="sys_save_selection" value="">
          <mxGeometry relative="1" as="geometry">
            <Array as="points">
              <mxPoint x="420" y="370" />
              <mxPoint x="420" y="345" />
            </Array>
          </mxGeometry>
        </mxCell>
        <mxCell id="edge11" edge="1" parent="1" source="peneliti_option4" style="edgeStyle=orthogonalEdgeStyle;rounded=0;orthogonalLoop=1;jettySize=auto;html=1;exitX=0.5;exitY=0;entryX=0;entryY=0.5;exitDx=0;exitDy=0;" target="sys_save_selection" value="">
          <mxGeometry relative="1" as="geometry">
            <Array as="points">
              <mxPoint x="400" y="380" />
              <mxPoint x="420" y="380" />
              <mxPoint x="420" y="345" />
            </Array>
          </mxGeometry>
        </mxCell>
        <mxCell id="edge12" edge="1" parent="1" source="sys_save_selection" style="edgeStyle=orthogonalEdgeStyle;rounded=0;orthogonalLoop=1;jettySize=auto;html=1;exitX=0.5;exitY=1;entryX=0.5;entryY=0;" target="sys_show_success" value="">
          <mxGeometry relative="1" as="geometry" />
        </mxCell>
        <mxCell id="edge13" edge="1" parent="1" source="sys_show_success" style="edgeStyle=orthogonalEdgeStyle;rounded=0;orthogonalLoop=1;jettySize=auto;html=1;exitX=0;exitY=0.5;entryX=1;entryY=0.5;entryDx=0;entryDy=0;" target="peneliti_view_result" value="">
          <mxGeometry relative="1" as="geometry">
            <Array as="points">
              <mxPoint x="580" y="470" />
              <mxPoint x="540" y="470" />
              <mxPoint x="540" y="525" />
            </Array>
          </mxGeometry>
        </mxCell>
        <mxCell id="edge14" edge="1" parent="1" source="peneliti_view_result" style="edgeStyle=orthogonalEdgeStyle;rounded=0;orthogonalLoop=1;jettySize=auto;html=1;" target="end" value="">
          <mxGeometry relative="1" as="geometry">
            <Array as="points">
              <mxPoint x="210" y="575" />
            </Array>
          </mxGeometry>
        </mxCell>
        <mxCell id="o7OUffk_LBbmV5dmaoma-2" parent="1" style="swimlane;whiteSpace=wrap;html=1;fontStyle=1;fontSize=14;startSize=23;" value="Peneliti Pemilihan&amp;nbsp;&lt;span style=&quot;background-color: transparent; color: light-dark(rgb(0, 0, 0), rgb(255, 255, 255));&quot;&gt;Process&lt;/span&gt;" vertex="1">
          <mxGeometry height="593" width="840" x="40" y="17" as="geometry" />
        </mxCell>
      </root>
    </mxGraphModel>
  </diagram>
</mxfile>
